mcp_mistral_ocr/__init__.py
mcp_mistral_ocr/main.py
mcp_mistral_ocr/mistral_ocr.py
mseep_mcp_mistral_ocr-1.0.3.dist-info/METADATA
mseep_mcp_mistral_ocr-1.0.3.dist-info/WHEEL
mseep_mcp_mistral_ocr-1.0.3.dist-info/RECORD
