Metadata-Version: 2.4
Name: mseep-mcp-mistral-ocr
Version: 1.0.3
Summary: MCP Server for OCR processing using Mistral AI
Author-email: mseep <support@skydeck.ai>
Requires-Dist: aiohttp
Requires-Dist: mcp[cli]
Requires-Dist: mistralai>=1.5.1
Requires-Dist: python-dotenv
Provides-Extra: dev
Requires-Dist: black; extra == 'dev'
Requires-Dist: isort; extra == 'dev'
Requires-Dist: mypy; extra == 'dev'
Requires-Dist: pytest; extra == 'dev'
Requires-Dist: pytest-asyncio; extra == 'dev'
